LICENSE
README.md
setup.py
aiomaxgram/__init__.py
aiomaxgram/api.py
aiomaxgram/bot.py
aiomaxgram/context.py
aiomaxgram/keyboards.py
aiomaxgram/types.py
aiomaxgram.egg-info/PKG-INFO
aiomaxgram.egg-info/SOURCES.txt
aiomaxgram.egg-info/dependency_links.txt
aiomaxgram.egg-info/requires.txt
aiomaxgram.egg-info/top_level.txt
aiomaxgram/core/__init__.py
aiomaxgram/core/helpers/__init__.py
aiomaxgram/core/network/__init__.py
aiomaxgram/core/network/client.py
aiomaxgram/core/network/polling.py